schema_miner/__init__.py
schema_miner/config/envConfig.py
schema_miner/config/llmRegistry.py
schema_miner/config/processConfig.py
schema_miner/ontology_grounding/__init__.py
schema_miner/ontology_grounding/agentic_qudt_grounding.py
schema_miner/ontology_grounding/prompt_qudt_grounding.py
schema_miner/pdf_text_extractor/__init__.py
schema_miner/pdf_text_extractor/extract_text.py
schema_miner/prompts/ontology_grounding/agent_qudt_prompt1.py
schema_miner/prompts/ontology_grounding/agent_qudt_prompt2.py
schema_miner/prompts/ontology_grounding/prompt_template.py
schema_miner/prompts/schema_extraction/prompt_template1.py
schema_miner/prompts/schema_extraction/prompt_template2.py
schema_miner/prompts/schema_extraction/prompt_template3.py
schema_miner/schema_extractor/__init__.py
schema_miner/schema_extractor/extract_schema.py
schema_miner/schemas/QUDT_quantity_schema.json
schema_miner/schemas/QUDT_quantity_schema_example.json
schema_miner/services/LLM_Inference/LLM_inference.py
schema_miner/services/LLM_Inference/huggingface_llm_inference.py
schema_miner/services/LLM_Inference/inference_runner.py
schema_miner/services/LLM_Inference/ollama_llm_inference.py
schema_miner/services/LLM_Inference/openai_llm_inference.py
schema_miner/services/LLM_Inference/saia_llm_inference.py
schema_miner/services/PDF_Parsers/PyPDF_pdf_parser.py
schema_miner/services/PDF_Parsers/docling_pdf_parser.py
schema_miner/services/PDF_Parsers/pdf_parser.py
schema_miner/services/ontology/ontology_manager.py
schema_miner/services/ontology/ontology_parser.py
schema_miner/services/schema_manager/schema_manager.py
schema_miner/utils/dictionary_utils.py
schema_miner/utils/evaluation_utils.py
schema_miner/utils/file_utils.py
schema_miner/utils/json_utils.py
schema_miner-2.0.2.dist-info/licenses/LICENSE.txt
schema_miner-2.0.2.dist-info/METADATA
schema_miner-2.0.2.dist-info/WHEEL
schema_miner-2.0.2.dist-info/top_level.txt
schema_miner-2.0.2.dist-info/RECORD
