Metadata-Version: 2.4
Name: schema_miner
Version: 2.0.2
Summary: A Human-in-the-Loop Workflow for Scientific Schema Mining with Large Language Models
Author-email: Sameer Sadruddin <sameer.sadruddin@tib.eu>, Jennifer D'Souza <jennifer.dsouza@tib.eu>
Maintainer-email: Sameer Sadruddin <sameer.sadruddin@tib.eu>
License-Expression: MIT
Project-URL: homepage, https://github.com/sciknoworg/schema-miner
Project-URL: repository, https://github.com/sciknoworg/schema-miner
Project-URL: Documentation, https://schema-miner.readthedocs.io
Keywords: Schema Discovery,Schema Mining,Scientific Schemas,Large Language Models,Human-in-the-loop Workflow
Requires-Python: >=3.12
License-File: LICENSE.txt
Requires-Dist: evaluate>=0.4.3
Requires-Dist: langchain_community>=0.3.14
Requires-Dist: langchain_core>=0.3.29
Requires-Dist: langchain_ollama>=0.2.2
Requires-Dist: langchain_openai>=0.3.0
Requires-Dist: langchain-huggingface>=0.1.2
Requires-Dist: pandas>=2.2.3
Requires-Dist: python-dotenv>=1.0.1
Requires-Dist: PyYAML>=6.0.2
Requires-Dist: transformers>=4.48.0
Requires-Dist: rdflib>=7.1.4
Requires-Dist: docling>=2.28.4
Requires-Dist: faiss-cpu>=1.10.0
Requires-Dist: sphinx>=8.1.3
Requires-Dist: sphinx-rtd-theme>=3.0.2
Dynamic: license-file
